{"name":"Calculus 1","code":"MAST10005","year":"2017","data":[{"sem":"SM1","data":[["P01/42","Monday","12:00pm - 1:00pm","PAR-David Caro-Podium 203",1],["P01/22","Monday","2:15pm - 3:15pm","PAR-David Caro-Podium 204",1],["L01/01","Monday","09:00am - 10:00am","PAR-Peter Hall-G01 (JH Michell Theatre)",1],["L01/03","Monday","3:15pm - 4:15pm","PAR-Peter Hall-G01 (JH Michell Theatre)",1],["P01/05","Monday","10:00am - 11:00am","PAR-Peter Hall-G11",1],["P01/33","Monday","4:15pm - 5:15pm","PAR-Peter Hall-G11",1],["P01/04","Monday","10:00am - 11:00am","PAR-Peter Hall-G14",1],["P01/06","Monday","1:00pm - 2:00pm","PAR-Peter Hall-G14",1],["P01/07","Monday","2:15pm - 3:15pm","PAR-Peter Hall-G14",1],["P01/32","Monday","4:15pm - 5:15pm","PAR-Peter Hall-G14",1],["P01/49","Monday","4:15pm - 5:15pm","PAR-Peter Hall-G50",1],["W01/13","Monday","09:00am - 10:00am","PAR-Peter Hall-M01 (Russell Love Theatre)",1],["W01/03","Monday","10:00am - 11:00am","PAR-Peter Hall-M01 (Russell Love Theatre)",1],["W01/02","Monday","12:00pm - 1:00pm","PAR-Peter Hall-M01 (Russell Love Theatre)",1],["W01/15","Monday","3:15pm - 4:15pm","PAR-Peter Hall-M01 (Russell Love Theatre)",1],["P01/14","Tuesday","10:00am - 11:00am","PAR-David Caro-Podium 203",1],["P01/10","Tuesday","11:00am - 12:00pm","PAR-David Caro-Podium 203",1],["P01/46","Tuesday","3:15pm - 4:15pm","PAR-David Caro-Podium 204",1],["P01/21","Tuesday","2:15pm - 3:15pm","PAR-Peter Hall-G09 (Math D)",1],["P01/11","Tuesday","2:15pm - 3:15pm","PAR-Peter Hall-G10 (Math C)",1],["P01/09","Tuesday","4:15pm - 5:15pm","PAR-Peter Hall-G10 (Math C)",1],["P01/25","Tuesday","09:00am - 10:00am","PAR-Peter Hall-G11",1],["P01/51","Tuesday","3:15pm - 4:15pm","PAR-Peter Hall-G11",1],["P01/39","Tuesday","4:15pm - 5:15pm","PAR-Peter Hall-G11",1],["P01/43","Tuesday","3:15pm - 4:15pm","PAR-Peter Hall-G14",1],["W01/09","Tuesday","09:00am - 10:00am","PAR-Peter Hall-M01 (Russell Love Theatre)",1],["W01/11","Tuesday","4:15pm - 5:15pm","PAR-Peter Hall-M01 (Russell Love Theatre)",1],["L01/02","Tuesday","1:00pm - 2:00pm","PAR-Sidney Myer Asia Ctr-B02 (Carrillo Gantner Theatre)",1],["P01/20","Wednesday","12:00pm - 1:00pm","PAR-David Caro-Podium 202",1],["P01/30","Wednesday","10:00am - 11:00am","PAR-David Caro-Podium 203",1],["P01/19","Wednesday","11:00am - 12:00pm","PAR-David Caro-Podium 203",1],["P01/13","Wednesday","4:15pm - 5:15pm","PAR-David Caro-Podium 203",1],["L02/01","Wednesday","09:00am - 10:00am","PAR-Peter Hall-G01 (JH Michell Theatre)",1],["L02/03","Wednesday","3:15pm - 4:15pm","PAR-Peter Hall-G01 (JH Michell Theatre)",1],["P01/17","Wednesday","12:00pm - 1:00pm","PAR-Peter Hall-G09 (Math D)",1],["P01/31","Wednesday","10:00am - 11:00am","PAR-Peter Hall-G10 (Math C)",1],["P01/26","Wednesday","1:00pm - 2:00pm","PAR-Peter Hall-G10 (Math C)",1],["P01/40","Wednesday","2:15pm - 3:15pm","PAR-Peter Hall-G10 (Math C)",1],["P01/15","Wednesday","2:15pm - 3:15pm","PAR-Peter Hall-G11",1],["P01/12","Wednesday","4:15pm - 5:15pm","PAR-Peter Hall-G14",1],["P01/52","Wednesday","4:15pm - 5:15pm","PAR-Peter Hall-G50",1],["W01/16","Wednesday","09:00am - 10:00am","PAR-Peter Hall-M01 (Russell Love Theatre)",1],["W01/07","Wednesday","10:00am - 11:00am","PAR-Peter Hall-M01 (Russell Love Theatre)",1],["W01/08","Wednesday","11:00am - 12:00pm","PAR-Peter Hall-M01 (Russell Love Theatre)",1],["W01/05","Wednesday","1:00pm - 2:00pm","PAR-Peter Hall-M01 (Russell Love Theatre)",1],["P01/28","Thursday","09:00am - 10:00am","PAR-David Caro-Podium 203",1],["P01/01","Thursday","10:00am - 11:00am","PAR-Peter Hall-G09 (Math D)",1],["P01/02","Thursday","3:15pm - 4:15pm","PAR-Peter Hall-G11",1],["P01/36","Thursday","4:15pm - 5:15pm","PAR-Peter Hall-G11",1],["P01/23","Thursday","2:15pm - 3:15pm","PAR-Peter Hall-G14",1],["P01/29","Thursday","4:15pm - 5:15pm","PAR-Peter Hall-G14",1],["P01/48","Thursday","10:00am - 11:00am","PAR-Peter Hall-G50",1],["P01/24","Thursday","11:00am - 12:00pm","PAR-Peter Hall-G50",1],["P01/45","Thursday","1:00pm - 2:00pm","PAR-Peter Hall-G50",1],["W01/10","Thursday","09:00am - 10:00am","PAR-Peter Hall-M01 (Russell Love Theatre)",1],["W01/01","Thursday","10:00am - 11:00am","PAR-Peter Hall-M01 (Russell Love Theatre)",1],["W01/14","Thursday","12:00pm - 1:00pm","PAR-Peter Hall-M01 (Russell Love Theatre)",1],["L02/02","Thursday","3:15pm - 4:15pm","PAR-The Spot-B01 (Copland Theatre)",1],["L03/02","Friday","4:15pm - 5:15pm","PAR-Arts West West Wing-B101 (Kathleen Fitzpatrick Theatre)",1],["P01/08","Friday","11:00am - 12:00pm","PAR-David Caro-Podium 204",1],["P01/34","Friday","10:00am - 11:00am","PAR-Peter Hall-215",1],["P01/03","Friday","12:00pm - 1:00pm","PAR-Peter Hall-215",1],["L03/01","Friday","09:00am - 10:00am","PAR-Peter Hall-G01 (JH Michell Theatre)",1],["L03/03","Friday","3:15pm - 4:15pm","PAR-Peter Hall-G01 (JH Michell Theatre)",1],["P01/47","Friday","12:00pm - 1:00pm","PAR-Peter Hall-G09 (Math D)",1],["P01/41","Friday","1:00pm - 2:00pm","PAR-Peter Hall-G11",1],["P01/44","Friday","2:15pm - 3:15pm","PAR-Peter Hall-G11",1],["P01/16","Friday","3:15pm - 4:15pm","PAR-Peter Hall-G11",1],["P01/35","Friday","4:15pm - 5:15pm","PAR-Peter Hall-G11",1],["P01/37","Friday","10:00am - 11:00am","PAR-Peter Hall-G14",1],["P01/38","Friday","1:00pm - 2:00pm","PAR-Peter Hall-G14",1],["P01/50","Friday","09:00am - 10:00am","PAR-Peter Hall-G50",1],["W01/12","Friday","10:00am - 11:00am","PAR-Peter Hall-M01 (Russell Love Theatre)",1],["W01/06","Friday","12:00pm - 1:00pm","PAR-Peter Hall-M01 (Russell Love Theatre)",1],["W01/17","Friday","1:00pm - 2:00pm","PAR-Peter Hall-M01 (Russell Love Theatre)",1],["W01/04","Friday","2:15pm - 3:15pm","PAR-Peter Hall-M01 (Russell Love Theatre)",1]]},{"sem":"SM2","data":[["P01/01","Monday","11:00am - 12:00pm","PAR-David Caro-Podium 202",1],["P01/24","Monday","10:00am - 11:00am","PAR-Peter Hall-215",1],["P01/22","Monday","3:15pm - 4:15pm","PAR-Peter Hall-G09 (Math D)",1],["P01/18","Monday","1:00pm - 2:00pm","PAR-Peter Hall-G11",1],["P01/02","Monday","12:00pm - 1:00pm","PAR-Peter Hall-G14",1],["P01/03","Tuesday","11:00am - 12:00pm","PAR-David Caro-Podium 202",1],["L01/01","Tuesday","2:15pm - 3:15pm","PAR-Old Arts-122 (Public Lecture Theatre - PLT)",1],["P01/04","Tuesday","09:00am - 10:00am","PAR-Peter Hall-215",1],["P01/06","Tuesday","3:15pm - 4:15pm","PAR-Peter Hall-G09 (Math D)",1],["P01/07","Tuesday","4:15pm - 5:15pm","PAR-Peter Hall-G10 (Math C)",1],["P01/05","Tuesday","11:00am - 12:00pm","PAR-Peter Hall-G11",1],["W01/04","Tuesday","3:15pm - 4:15pm","PAR-Peter Hall-M01 (Russell Love Theatre)",1],["P01/12","Wednesday","3:15pm - 4:15pm","PAR-Peter Hall-215",1],["P01/16","Wednesday","1:00pm - 2:00pm","PAR-Peter Hall-G09 (Math D)",1],["P01/11","Wednesday","2:15pm - 3:15pm","PAR-Peter Hall-G09 (Math D)",1],["P01/13","Wednesday","4:15pm - 5:15pm","PAR-Peter Hall-G10 (Math C)",1],["P01/09","Wednesday","11:00am - 12:00pm","PAR-Peter Hall-G11",1],["P01/23","Wednesday","10:00am - 11:00am","PAR-Peter Hall-G14",1],["P01/10","Wednesday","12:00pm - 1:00pm","PAR-Peter Hall-G14",1],["W01/05","Wednesday","09:00am - 10:00am","PAR-Peter Hall-M01 (Russell Love Theatre)",1],["W01/02","Wednesday","10:00am - 11:00am","PAR-Peter Hall-M01 (Russell Love Theatre)",1],["W01/06","Wednesday","3:15pm - 4:15pm","PAR-Peter Hall-M01 (Russell Love Theatre)",1],["P01/21","Thursday","4:15pm - 5:15pm","PAR-David Caro-Podium 202",1],["P01/17","Thursday","2:15pm - 3:15pm","PAR-Peter Hall-G09 (Math D)",1],["P01/15","Thursday","10:00am - 11:00am","PAR-Peter Hall-G14",1],["W01/01","Thursday","09:00am - 10:00am","PAR-Peter Hall-M01 (Russell Love Theatre)",1],["W01/03","Thursday","12:00pm - 1:00pm","PAR-Peter Hall-M01 (Russell Love Theatre)",1],["W01/07","Thursday","3:15pm - 4:15pm","PAR-Peter Hall-M01 (Russell Love Theatre)",1],["L02/01","Thursday","11:00am - 12:00pm","PAR-Sidney Myer Asia Ctr-B02 (Carrillo Gantner Theatre)",1],["P01/25","Friday","09:00am - 10:00am","PAR-Peter Hall-215",1],["P01/19","Friday","2:15pm - 3:15pm","PAR-Peter Hall-G09 (Math D)",1],["P01/20","Friday","3:15pm - 4:15pm","PAR-Peter Hall-G10 (Math C)",1],["W01/08","Friday","2:15pm - 3:15pm","PAR-Peter Hall-M01 (Russell Love Theatre)",1],["L03/01","Friday","11:00am - 12:00pm","PAR-The Spot-B01 (Copland Theatre)",1]]}]}